s3_browser/__init__.py
s3_browser/argparse.py
s3_browser/bookmarks.py
s3_browser/cli.py
s3_browser/client.py
s3_browser/completion.py
s3_browser/paths.py
s3_browser/ps1.py
s3_browser/tokeniser.py
s3_browser/utils.py
s3_browser-0.5.2.dist-info/licenses/LICENSE
s3_browser-0.5.2.dist-info/METADATA
s3_browser-0.5.2.dist-info/WHEEL
s3_browser-0.5.2.dist-info/entry_points.txt
s3_browser-0.5.2.dist-info/top_level.txt
s3_browser-0.5.2.dist-info/RECORD
