Metadata-Version: 2.4
Name: s3_browser
Version: 0.5.2
Summary: An interactive tool to browse s3 like a regular directory structure
Author-email: Rob Moore <giftiger.wunsch@gmail.com>
Project-URL: Repository, https://github.com/giftig/s3-browser/
Keywords: aws,s3,browser,cli,interactive,prompt,s3-browser
Classifier: Development Status :: 4 - Beta
Classifier: Environment :: Console
Classifier: Intended Audience :: Developers
Classifier: Intended Audience :: System Administrators
Classifier: Natural Language :: English
Classifier: Operating System :: OS Independent
Classifier: Programming Language :: Python :: 3
Classifier: Programming Language :: Python :: 3 :: Only
Classifier: Programming Language :: Python :: Implementation :: PyPy
Classifier: Topic :: Internet
Classifier: Topic :: Terminals
Classifier: Topic :: Utilities
Requires-Python: >=3.7
License-File: LICENSE
Requires-Dist: boto3>=1.9.0
Requires-Dist: prompt-toolkit>=3.0.48
Requires-Dist: python-magic>=0.4.27
Dynamic: license-file
